checkmark/__init__.py
checkmark/form.py
checkmark/inlines.py
checkmark/link.py
checkmark/lists/__init__.py
checkmark/lists/dropdown.py
checkmark/lists/radio.py
checkmark/namedlist.py
checkmark/parser.py
checkmark/templates.py
checkmark-1.7.4.dist-info/LICENSE
checkmark-1.7.4.dist-info/WHEEL
checkmark-1.7.4.dist-info/METADATA
checkmark-1.7.4.dist-info/RECORD
