Metadata-Version: 2.1
Name: checkmark
Version: 1.7.4
Summary: Create launchable HTML form windows in Markdown
Home-page: https://gitlab.com/deepadmax/checkmark
License: GPL-3.0-or-later
Author: Maximillian Strand
Author-email: maximillian.strand@protonmail.com
Requires-Python: >=3.9,<4.0
Classifier: License :: OSI Approved :: GNU General Public License v3 or later (GPLv3+)
Classifier: Programming Language :: Python :: 3
Classifier: Programming Language :: Python :: 3.10
Classifier: Programming Language :: Python :: 3.9
Requires-Dist: pywebview (>=3.5,<4.0)
Project-URL: Repository, https://gitlab.com/deepadmax/checkmark
